captcha_ai_solver-0.2.0.dist-info/licenses/LICENSE
captcha_solver/__init__.py
captcha_solver/audio_challenge_solver.py
captcha_solver/captcha_replicator.py
captcha_solver/captcha_solver.py
captcha_solver/hosts_manager.py
captcha_ai_solver-0.2.0.dist-info/METADATA
captcha_ai_solver-0.2.0.dist-info/WHEEL
captcha_ai_solver-0.2.0.dist-info/top_level.txt
captcha_ai_solver-0.2.0.dist-info/RECORD
