Metadata-Version: 2.4
Name: captcha-ai-solver
Version: 0.2.0
Summary: A powerful AI-based library for solving reCAPTCHA challenges
Author-email: "@njraladdin" <aladynjr@gmail.com>
Keywords: captcha,recaptcha,automation,selenium,ai,solver
Requires-Python: >=3.7
License-File: LICENSE
Requires-Dist: seleniumbase
Requires-Dist: requests
Requires-Dist: python-dotenv
Requires-Dist: flask>=2.0.0
Requires-Dist: pyOpenSSL
Provides-Extra: dev
Requires-Dist: black; extra == "dev"
Dynamic: license-file
